smolantic_ai/__init__.py
smolantic_ai/_version.py
smolantic_ai/agent.py
smolantic_ai/code_agent.py
smolantic_ai/config.py
smolantic_ai/continuous_agent.py
smolantic_ai/exceptions.py
smolantic_ai/executors.py
smolantic_ai/logging.py
smolantic_ai/models.py
smolantic_ai/multistep_agent.py
smolantic_ai/prebuilt_tools.py
smolantic_ai/prompts.py
smolantic_ai/utils.py
smolantic_ai-1.0.2.dist-info/METADATA
smolantic_ai-1.0.2.dist-info/WHEEL
smolantic_ai-1.0.2.dist-info/licenses/LICENSE
smolantic_ai-1.0.2.dist-info/RECORD
