Metadata-Version: 2.4
Name: smolantic-ai
Version: 1.0.2
Summary: A Python framework leveraging pydantic-ai to build specialized AI agents for multi-step task processing, tool calling, and code generation/execution
Project-URL: Homepage, https://github.com/esragoth/smolantic_ai
Project-URL: Documentation, https://github.com/esragoth/smolantic_ai#readme
Project-URL: Repository, https://github.com/esragoth/smolantic_ai.git
Author-email: Esra Goth <beppe.wizzy@gmail.com>
License: MIT
License-File: LICENSE
Classifier: Development Status :: 3 - Alpha
Classifier: Intended Audience :: Developers
Classifier: License :: OSI Approved :: MIT License
Classifier: Programming Language :: Python :: 3
Classifier: Programming Language :: Python :: 3.8
Classifier: Programming Language :: Python :: 3.9
Classifier: Programming Language :: Python :: 3.10
Classifier: Programming Language :: Python :: 3.11
Classifier: Topic :: Scientific/Engineering :: Artificial Intelligence
Classifier: Topic :: Software Development :: Libraries :: Python Modules
Requires-Python: >=3.8
Requires-Dist: anthropic>=0.18.0
Requires-Dist: docker>=6.0.0
Requires-Dist: e2b>=0.1.0
Requires-Dist: google-generativeai>=0.3.0
Requires-Dist: jinja2>=3.1.0
Requires-Dist: matplotlib>=3.7.0
Requires-Dist: numpy>=1.24.0
Requires-Dist: openai>=1.0.0
Requires-Dist: pydantic-ai>=0.8.1
Requires-Dist: pydantic-settings>=2.0.0
Requires-Dist: pydantic>=2.0.0
Requires-Dist: python-dotenv>=1.0.0
Requires-Dist: requests>=2.20.0
Provides-Extra: dev
Requires-Dist: black>=23.0; extra == 'dev'
Requires-Dist: flake8>=6.0; extra == 'dev'
Requires-Dist: isort>=5.0; extra == 'dev'
Requires-Dist: pytest-cov>=4.0; extra == 'dev'
Requires-Dist: pytest>=7.0; extra == 'dev'
